MANIFEST.in
README.rst
setup.py
data/benchmarks/cfd.conf
data/benchmarks/dacapo.conf
data/benchmarks/filebench.conf
data/benchmarks/iperf-client.conf
data/benchmarks/iperf.conf
data/benchmarks/sysbench.conf
data/benchmarks/testing.conf
data/benchmarks/web-frameworks.conf
data/benchmarks/ycsb-mongodb.conf
data/benchmarks/ycsb-mysql.conf
data/providers/amazon.conf.example
data/providers/existing_vm.conf.example
data/providers/openstack.conf.example
src/benchsuite/__init__.py
src/benchsuite.stdlib.egg-info/PKG-INFO
src/benchsuite.stdlib.egg-info/SOURCES.txt
src/benchsuite.stdlib.egg-info/dependency_links.txt
src/benchsuite.stdlib.egg-info/namespace_packages.txt
src/benchsuite.stdlib.egg-info/requires.txt
src/benchsuite.stdlib.egg-info/top_level.txt
src/benchsuite/stdlib/__init__.py
src/benchsuite/stdlib/benchmark/__init__.py
src/benchsuite/stdlib/benchmark/parsers.py
src/benchsuite/stdlib/benchmark/vm_benchmark.py
src/benchsuite/stdlib/execution/__init__.py
src/benchsuite/stdlib/execution/sshexecutor.py
src/benchsuite/stdlib/execution/vm_environment.py
src/benchsuite/stdlib/provider/__init__.py
src/benchsuite/stdlib/provider/existing_vm.py
src/benchsuite/stdlib/provider/libcloud.py
src/benchsuite/stdlib/util/__init__.py
src/benchsuite/stdlib/util/libcloud_helper.py
src/benchsuite/stdlib/util/ssh.py
src/benchsuite/stdlib/util/timeutils.py